enova/llmo/__init__.py
enova/llmo/instrumentation/__init__.py
enova/llmo/instrumentation/fastapi/__init__.py
enova/llmo/instrumentation/vllm/__init__.py
enova/llmo/instrumentation/vllm/wrappers.py
enova/llmo/metrics_adapter/__init__.py
enova/llmo/metrics_adapter/vllm_logging_metrics.py
enova_instrumentation_llmo-0.0.7.dist-info/WHEEL
enova_instrumentation_llmo-0.0.7.dist-info/METADATA
enova_instrumentation_llmo-0.0.7.dist-info/RECORD
